hparam
